<?xml version="1.0" encoding="utf-8"?>
<!-- GENERATED BY: PLM XML SDK 7.0.4.418 -->
<PLMXML xmlns="http://www.plmxml.org/Schemas/PLMXMLSchema"
 language="en-us" time="10:59:19" schemaVersion="6" author="Teamcenter V11000.2.3.31_20170523.00 - testuser1@Central-Site Productive Database(1400794284)" date="2017-08-11">
<Header id="id1" traverseRootRefs="#id3 #id11 #id22 #id32 #id39 #id58 #id69 #id57 #id56 #id55 #id54 #id53 #id52 #id51 #id50 #id49 #id48 #id47 #id168 #id167 #id166 #id165 #id190 #id2" transferContext="workflow_template_mode"></Header>
<WorkflowTemplate id="id2" name="PR" subTemplateRefs="#id3 #id11 #id22 #id32 #id39 #id47 #id55 #id69 #id165 #id50 #id58 #id57 #id166 #id167 #id53 #id49 #id48 #id190 #id52 #id168 #id51 #id54 #id56" originalId="CWVlhu5n1cuxKD" signoffQuorum="0" objectType="EPMTaskTemplate" iconKey="process" dependencyTaskTemplateRefs="#id190" showInProcessStage="true" location="0,0,0,6e,4a2,104" templateClassification="process" actions="#id194 #id219 #id227">
<ApplicationRef application="Teamcenter" label="jBYlYfaa1cuxKD" version="jBYlYfaa1cuxKD"></ApplicationRef>
<UserData id="id193" type="reference">
<UserValue title="completeDependencyTaskRef" value="4" dataRef="#id190"></UserValue></UserData></WorkflowTemplate>
<WorkflowTemplate id="id3" name="check Owning Group" originalId="Ceclhu5n1cuxKD" signoffQuorum="0" parentTaskTemplateRef="#id2" objectType="EPMConditionTaskTemplate" iconKey="conditionTask" dependencyTaskTemplateRefs="#id2" showInProcessStage="true" location="11,1f3,4,64,26c,64" actions="#id5 #id8">
<ApplicationRef application="Teamcenter" label="jVQlYfaa1cuxKD" version="jVQlYfaa1cuxKD"></ApplicationRef>
<UserData id="id4" type="reference">
<UserValue title="parentDependencyTaskRef" value="202" dataRef="#id2"></UserValue></UserData></WorkflowTemplate>
<WorkflowAction id="id5" parentRef="" actionType="4" ruleRefs="#id6">
<ApplicationRef application="Teamcenter" label="jVRlYfaa1cuxKD" version="jVRlYfaa1cuxKD"></ApplicationRef></WorkflowAction>
<WorkflowBusinessRule id="id6" ruleQuorum="1" ruleHandlerRefs="#id7">
<ApplicationRef application="Teamcenter" label="jVSlYfaa1cuxKD" version="jVSlYfaa1cuxKD"></ApplicationRef></WorkflowBusinessRule>
<WorkflowBusinessRuleHandler id="id7" name="EPM-check-condition">
<ApplicationRef application="Teamcenter" label="jVUlYfaa1cuxKD" version="jVUlYfaa1cuxKD"></ApplicationRef></WorkflowBusinessRuleHandler>
<WorkflowAction id="id8" actionHandlerRefs="#id9" parentRef="" actionType="2">
<ApplicationRef application="Teamcenter" label="jVYlYfaa1cuxKD" version="jVYlYfaa1cuxKD"></ApplicationRef></WorkflowAction>
<WorkflowHandler id="id9" name="EPM-set-condition">
<ApplicationRef application="Teamcenter" label="jVZlYfaa1cuxKD" version="jVZlYfaa1cuxKD"></ApplicationRef>
<Arguments id="id10" type="string">
<UserValue title="handler_argument" value="-query=__WF_SBT_Check_OwningGroup"></UserValue>
<UserValue title="handler_argument" value="-check_targets=any"></UserValue></Arguments></WorkflowHandler>
<WorkflowTemplate id="id11" name="Fehler Owning Goup" originalId="CmUlhu5n1cuxKD" signoffQuorum="0" parentTaskTemplateRef="#id2" objectType="EPMDoTaskTemplate" iconKey="doTask" dependencyTaskTemplateRefs="#id3" showInProcessStage="true" location="d2,1ef,4,64,26c,64" actions="#id14 #id17">
<ApplicationRef application="Teamcenter" label="jVdlYfaa1cuxKD" version="jVdlYfaa1cuxKD"></ApplicationRef>
<UserData id="id13" type="reference">
<UserValue title="startDependencyTaskRef" value="2" dataRef="#id3"></UserValue></UserData>
<TaskDescription id="id12">
<Item value="Falscher Eigentümer!&#xA;&#xA;Sie dürfen nur Änderungsstände der eigenen Gruppe freigeben.&#xA;Bitte den Prozess löschen oder diesen Task abschließen."></Item></TaskDescription></WorkflowTemplate>
<WorkflowAction id="id14" parentRef="" actionType="4" ruleRefs="#id15">
<ApplicationRef application="Teamcenter" label="jVelYfaa1cuxKD" version="jVelYfaa1cuxKD"></ApplicationRef></WorkflowAction>
<WorkflowBusinessRule id="id15" ruleQuorum="1" ruleHandlerRefs="#id16">
<ApplicationRef application="Teamcenter" label="jVflYfaa1cuxKD" version="jVflYfaa1cuxKD"></ApplicationRef></WorkflowBusinessRule>
<WorkflowBusinessRuleHandler id="id16" name="EPM-hold">
<ApplicationRef application="Teamcenter" label="jZRlYfaa1cuxKD" version="jZRlYfaa1cuxKD"></ApplicationRef></WorkflowBusinessRuleHandler>
<WorkflowAction id="id17" actionHandlerRefs="#id21" parentRef="" actionType="2" ruleRefs="#id18">
<ApplicationRef application="Teamcenter" label="jZVlYfaa1cuxKD" version="jZVlYfaa1cuxKD"></ApplicationRef></WorkflowAction>
<WorkflowBusinessRule id="id18" ruleQuorum="-1" ruleHandlerRefs="#id19">
<ApplicationRef application="Teamcenter" label="jZWlYfaa1cuxKD" version="jZWlYfaa1cuxKD"></ApplicationRef></WorkflowBusinessRule>
<WorkflowBusinessRuleHandler id="id19" name="EPM-check-condition">
<ApplicationRef application="Teamcenter" label="jZYlYfaa1cuxKD" version="jZYlYfaa1cuxKD"></ApplicationRef>
<Arguments id="id20" type="string">
<UserValue title="handler_argument" value="-source_task=check Owning Group"></UserValue>
<UserValue title="handler_argument" value="-decision=true"></UserValue></Arguments></WorkflowBusinessRuleHandler>
<WorkflowHandler id="id21" name="EPM-inherit">
<ApplicationRef application="Teamcenter" label="jZblYfaa1cuxKD" version="jZblYfaa1cuxKD"></ApplicationRef></WorkflowHandler>
<WorkflowTemplate id="id22" name="Check BOM Precise" originalId="x3SlzRZa1cuxKD" signoffQuorum="0" parentTaskTemplateRef="#id2" objectType="EPMValidateTaskTemplate" iconKey="validateTask" dependencyTaskTemplateRefs="#id3" showInProcessStage="false" location="68,14e,4,64,26c,64" actions="#id24 #id28">
<ApplicationRef application="Teamcenter" label="jZflYfaa1cuxKD" version="jZflYfaa1cuxKD"></ApplicationRef>
<UserData id="id23" type="reference">
<UserValue title="startDependencyTaskRef" value="2" dataRef="#id3"></UserValue></UserData></WorkflowTemplate>
<WorkflowAction id="id24" parentRef="" actionType="2" ruleRefs="#id25">
<ApplicationRef application="Teamcenter" label="jdQlYfaa1cuxKD" version="jdQlYfaa1cuxKD"></ApplicationRef></WorkflowAction>
<WorkflowBusinessRule id="id25" ruleQuorum="-1" ruleHandlerRefs="#id26">
<ApplicationRef application="Teamcenter" label="jdRlYfaa1cuxKD" version="jdRlYfaa1cuxKD"></ApplicationRef></WorkflowBusinessRule>
<WorkflowBusinessRuleHandler id="id26" name="EPM-check-condition">
<ApplicationRef application="Teamcenter" label="jdTlYfaa1cuxKD" version="jdTlYfaa1cuxKD"></ApplicationRef>
<Arguments id="id27" type="string">
<UserValue title="handler_argument" value="-source_task=check Owning Group"></UserValue>
<UserValue title="handler_argument" value="-decision=false"></UserValue></Arguments></WorkflowBusinessRuleHandler>
<WorkflowAction id="id28" parentRef="" actionType="4" ruleRefs="#id29">
<ApplicationRef application="Teamcenter" label="jdXlYfaa1cuxKD" version="jdXlYfaa1cuxKD"></ApplicationRef></WorkflowAction>
<WorkflowBusinessRule id="id29" ruleQuorum="-1" ruleHandlerRefs="#id30">
<ApplicationRef application="Teamcenter" label="jdYlYfaa1cuxKD" version="jdYlYfaa1cuxKD"></ApplicationRef></WorkflowBusinessRule>
<WorkflowBusinessRuleHandler id="id30" name="TCPB-RH-checkBomPrecision">
<ApplicationRef application="Teamcenter" label="jdalYfaa1cuxKD" version="jdalYfaa1cuxKD"></ApplicationRef>
<Arguments id="id31" type="string">
<UserValue title="handler_argument" value="-check=precise"></UserValue>
<UserValue title="handler_argument" value="-maxdepth=1"></UserValue>
<UserValue title="handler_argument" value="-stop=y"></UserValue></Arguments></WorkflowBusinessRuleHandler>
<WorkflowTemplate id="id32" name="Check BOM Status" originalId="iQWlzRZa1cuxKD" signoffQuorum="0" parentTaskTemplateRef="#id2" objectType="EPMValidateTaskTemplate" iconKey="validateTask" dependencyTaskTemplateRefs="#id22" showInProcessStage="false" location="10b,14f,4,64,26c,64" actions="#id34 #id38">
<ApplicationRef application="Teamcenter" label="jdflYfaa1cuxKD" version="jdflYfaa1cuxKD"></ApplicationRef>
<UserData id="id33" type="reference">
<UserValue title="startDependencyTaskRef" value="2" dataRef="#id22"></UserValue></UserData></WorkflowTemplate>
<WorkflowAction id="id34" parentRef="" actionType="4" ruleRefs="#id35">
<ApplicationRef application="Teamcenter" label="jhQlYfaa1cuxKD" version="jhQlYfaa1cuxKD"></ApplicationRef></WorkflowAction>
<WorkflowBusinessRule id="id35" ruleQuorum="-1" ruleHandlerRefs="#id36">
<ApplicationRef application="Teamcenter" label="jhRlYfaa1cuxKD" version="jhRlYfaa1cuxKD"></ApplicationRef></WorkflowBusinessRule>
<WorkflowBusinessRuleHandler id="id36" name="TCPB-RH-checkBomChildStatusList">
<ApplicationRef application="Teamcenter" label="jhTlYfaa1cuxKD" version="jhTlYfaa1cuxKD"></ApplicationRef>
<Arguments id="id37" type="string">
<UserValue title="handler_argument" value="-rule=WF_Precise"></UserValue>
<UserValue title="handler_argument" value="-statelist=10,60,BT7_ECO"></UserValue>
<UserValue title="handler_argument" value="-check_job=n"></UserValue>
<UserValue title="handler_argument" value="-stop=y"></UserValue>
<UserValue title="handler_argument" value="-maxdepth=1"></UserValue></Arguments></WorkflowBusinessRuleHandler>
<WorkflowAction id="id38" parentRef="" actionType="2">
<ApplicationRef application="Teamcenter" label="jhXlYfaa1cuxKD" version="jhXlYfaa1cuxKD"></ApplicationRef></WorkflowAction>
<WorkflowTemplate id="id39" name="Notify" originalId="C6alzRZa1cuxKD" signoffQuorum="0" parentTaskTemplateRef="#id2" objectType="EPMTaskTemplate" iconKey="task" dependencyTaskTemplateRefs="#id32" showInProcessStage="false" location="19c,14b,4,64,26c,64" actions="#id41">
<ApplicationRef application="Teamcenter" label="jhalYfaa1cuxKD" version="jhalYfaa1cuxKD"></ApplicationRef>
<UserData id="id40" type="reference">
<UserValue title="failDependencyTaskRef" value="10" dataRef="#id32"></UserValue></UserData></WorkflowTemplate>
<WorkflowAction id="id41" actionHandlerRefs="#id45" parentRef="" actionType="2" ruleRefs="#id42">
<ApplicationRef application="Teamcenter" label="jhblYfaa1cuxKD" version="jhblYfaa1cuxKD"></ApplicationRef></WorkflowAction>
<WorkflowBusinessRule id="id42" ruleQuorum="-1" ruleHandlerRefs="#id43">
<ApplicationRef application="Teamcenter" label="jhclYfaa1cuxKD" version="jhclYfaa1cuxKD"></ApplicationRef></WorkflowBusinessRule>
<WorkflowBusinessRuleHandler id="id43" name="EPM-check-condition">
<ApplicationRef application="Teamcenter" label="jhelYfaa1cuxKD" version="jhelYfaa1cuxKD"></ApplicationRef>
<Arguments id="id44" type="string">
<UserValue title="handler_argument" value="-source_task=Check BOM Status"></UserValue>
<UserValue title="handler_argument" value="-decision=ANY"></UserValue></Arguments></WorkflowBusinessRuleHandler>
<WorkflowHandler id="id45" name="EPM-notify">
<ApplicationRef application="Teamcenter" label="jlRlYfaa1cuxKD" version="jlRlYfaa1cuxKD"></ApplicationRef>
<Arguments id="id46" type="string">
<UserValue title="handler_argument" value="-recipient=$PROCESS_OWNER"></UserValue>
<UserValue title="handler_argument" value="-subject=Teamcenter: ValidVersion Check"></UserValue>
<UserValue title="handler_argument" value="-comment=Workflow was aborted. Please check Precise BOM Structure. Valid Status are PR, PR+, SR."></UserValue>
<UserValue title="handler_argument" value="-url=activeworkspace"></UserValue>
<UserValue title="handler_argument" value="-attachment=target"></UserValue></Arguments></WorkflowHandler>
<WorkflowTemplate id="id47" name="Set Status PR" originalId="C2Tlhu5n1cuxKD" signoffQuorum="0" parentTaskTemplateRef="#id2" objectType="EPMAddStatusTaskTemplate" iconKey="addStatusTask" dependencyTaskTemplateRefs="#id48" showInProcessStage="true" location="29b,1e7,4,64,26c,64" actions="#id139 #id154">
<ApplicationRef application="Teamcenter" label="jlVlYfaa1cuxKD" version="jlVlYfaa1cuxKD"></ApplicationRef>
<UserData id="id138" type="reference">
<UserValue title="startDependencyTaskRef" value="2" dataRef="#id48"></UserValue></UserData></WorkflowTemplate>
<WorkflowTemplate id="id48" name=" Cleanup Relations 2 / 2" originalId="SKflhu5n1cuxKD" signoffQuorum="0" parentTaskTemplateRef="#id2" objectType="EPMTaskTemplate" iconKey="task" dependencyTaskTemplateRefs="#id49" showInProcessStage="false" location="286,249,4,64,26c,64" actions="#id133 #id136">
<ApplicationRef application="Teamcenter" label="zFflYfaa1cuxKD" version="zFflYfaa1cuxKD"></ApplicationRef>
<UserData id="id132" type="reference">
<UserValue title="startDependencyTaskRef" value="2" dataRef="#id49"></UserValue></UserData></WorkflowTemplate>
<WorkflowTemplate id="id49" name="Hold Parent Task" originalId="SWRlhu5n1cuxKD" signoffQuorum="0" parentTaskTemplateRef="#id2" objectType="EPMTaskTemplate" iconKey="task" dependencyTaskTemplateRefs="#id50" showInProcessStage="false" location="1d0,24b,4,64,26c,64" actions="#id131">
<ApplicationRef application="Teamcenter" label="zFblYfaa1cuxKD" version="zFblYfaa1cuxKD"></ApplicationRef>
<UserData id="id130" type="reference">
<UserValue title="startDependencyTaskRef" value="2" dataRef="#id50"></UserValue></UserData></WorkflowTemplate>
<WorkflowTemplate id="id50" name="Start Sub-Workflow for every target" originalId="SCblhu5n1cuxKD" signoffQuorum="0" parentTaskTemplateRef="#id2" objectType="EPMTaskTemplate" iconKey="task" dependencyTaskTemplateRefs="#id51" showInProcessStage="false" location="1aa,1ce,4,64,26c,64" actions="#id122 #id126">
<ApplicationRef application="Teamcenter" label="j5SlYfaa1cuxKD" version="j5SlYfaa1cuxKD"></ApplicationRef>
<UserData id="id121" type="reference">
<UserValue title="startDependencyTaskRef" value="2" dataRef="#id51"></UserValue></UserData></WorkflowTemplate>
<WorkflowTemplate id="id51" name="Already PreReleased?" originalId="SSWlhu5n1cuxKD" signoffQuorum="0" parentTaskTemplateRef="#id2" objectType="EPMConditionTaskTemplate" iconKey="conditionTask" dependencyTaskTemplateRefs="#id52" showInProcessStage="true" location="29d,71,4,64,26c,64" actions="#id116 #id120">
<ApplicationRef application="Teamcenter" label="zNelYfaa1cuxKD" version="zNelYfaa1cuxKD"></ApplicationRef>
<UserData id="id115" type="reference">
<UserValue title="startDependencyTaskRef" value="2" dataRef="#id52"></UserValue></UserData></WorkflowTemplate>
<WorkflowTemplate id="id52" name="Assign Distribution list(deactivated)" originalId="RGSlSIY81cuxKD" signoffQuorum="0" parentTaskTemplateRef="#id2" objectType="EPMDoTaskTemplate" iconKey="doTask" dependencyTaskTemplateRefs="#id53" showInProcessStage="true" location="1cc,6c,4,64,26c,64" actions="#id110">
<ApplicationRef application="Teamcenter" label="zJdlYfaa1cuxKD" version="zJdlYfaa1cuxKD"></ApplicationRef>
<UserData id="id109" type="reference">
<UserValue title="startDependencyTaskRef" value="2" dataRef="#id53"></UserValue></UserData></WorkflowTemplate>
<WorkflowTemplate id="id53" name="Condition OK?" originalId="SiSlhu5n1cuxKD" signoffQuorum="0" parentTaskTemplateRef="#id2" objectType="EPMConditionTaskTemplate" iconKey="conditionTask" dependencyTaskTemplateRefs="#id54" showInProcessStage="true" location="123,6f,4,64,26c,64" actions="#id106">
<ApplicationRef application="Teamcenter" label="zFVlYfaa1cuxKD" version="zFVlYfaa1cuxKD"></ApplicationRef>
<UserData id="id105" type="reference">
<UserValue title="startDependencyTaskRef" value="2" dataRef="#id54"></UserValue></UserData></WorkflowTemplate>
<WorkflowTemplate id="id54" name="Check BOM" originalId="SaSlhu5n1cuxKD" signoffQuorum="0" parentTaskTemplateRef="#id2" objectType="EPMDoTaskTemplate" iconKey="doTask" dependencyTaskTemplateRefs="#id55" showInProcessStage="true" location="1c5,8,4,64,26c,64" actions="#id98">
<ApplicationRef application="Teamcenter" label="zRZlYfaa1cuxKD" version="zRZlYfaa1cuxKD"></ApplicationRef>
<UserData id="id97" type="reference">
<UserValue title="startDependencyTaskRef" value="2" dataRef="#id55"></UserValue></UserData></WorkflowTemplate>
<WorkflowTemplate id="id55" name="Check Relation" originalId="CyRlhu5n1cuxKD" signoffQuorum="0" parentTaskTemplateRef="#id2" objectType="EPMConditionTaskTemplate" iconKey="conditionTask" dependencyTaskTemplateRefs="#id56" showInProcessStage="true" location="131,8,4,64,26c,64" actions="#id90 #id94">
<ApplicationRef application="Teamcenter" label="jtTlYfaa1cuxKD" version="jtTlYfaa1cuxKD"></ApplicationRef>
<UserData id="id89" type="reference">
<UserValue title="startDependencyTaskRef" value="2" dataRef="#id56"></UserValue></UserData></WorkflowTemplate>
<WorkflowTemplate id="id56" name="Cleanup Relations 1/2" originalId="Siflhu5n1cuxKD" signoffQuorum="0" parentTaskTemplateRef="#id2" objectType="EPMTaskTemplate" iconKey="task" dependencyTaskTemplateRefs="#id57" showInProcessStage="false" location="7e,9,4,64,26c,64" actions="#id84 #id87">
<ApplicationRef application="Teamcenter" label="zVXlYfaa1cuxKD" version="zVXlYfaa1cuxKD"></ApplicationRef>
<UserData id="id83" type="reference">
<UserValue title="startDependencyTaskRef" value="2" dataRef="#id57"></UserValue></UserData></WorkflowTemplate>
<WorkflowTemplate id="id57" name="Or 1" originalId="SWZlhu5n1cuxKD" signoffQuorum="0" parentTaskTemplateRef="#id2" objectType="EPMOrTaskTemplate" iconKey="orTask" dependencyTaskTemplateRefs="#id58 #id69 #id32 #id22" showInProcessStage="false" location="4c,70,4,64,26c,64" actions="#id79">
<ApplicationRef application="Teamcenter" label="j9blYfaa1cuxKD" version="j9blYfaa1cuxKD"></ApplicationRef>
<UserData id="id78" type="reference">
<UserValue title="startDependencyTaskRef" value="2" dataRef="#id58"></UserValue>
<UserValue title="startDependencyTaskRef" value="2" dataRef="#id69"></UserValue>
<UserValue title="startDependencyTaskRef" value="2" dataRef="#id32"></UserValue>
<UserValue title="failDependencyTaskRef" value="10" dataRef="#id22"></UserValue></UserData></WorkflowTemplate>
<WorkflowTemplate id="id58" name="Review Error Report" originalId="SGVlhu5n1cuxKD" signoffQuorum="0" parentTaskTemplateRef="#id2" objectType="EPMDoTaskTemplate" iconKey="doTask" dependencyTaskTemplateRefs="#id53" showInProcessStage="true" location="d0,f1,4,64,26c,64" actions="#id61 #id66">
<ApplicationRef application="Teamcenter" label="j1QlYfaa1cuxKD" version="j1QlYfaa1cuxKD"></ApplicationRef>
<UserData id="id60" type="reference">
<UserValue title="startDependencyTaskRef" value="2" dataRef="#id53"></UserValue></UserData>
<TaskDescription id="id59">
<Item value="Condition is not fullfilled, please refer to the report attached to this workflow."></Item></TaskDescription></WorkflowTemplate>
<WorkflowAction id="id61" actionHandlerRefs="#id65" parentRef="" actionType="2" ruleRefs="#id62">
<ApplicationRef application="Teamcenter" label="j1RlYfaa1cuxKD" version="j1RlYfaa1cuxKD"></ApplicationRef></WorkflowAction>
<WorkflowBusinessRule id="id62" ruleQuorum="-1" ruleHandlerRefs="#id63">
<ApplicationRef application="Teamcenter" label="j1SlYfaa1cuxKD" version="j1SlYfaa1cuxKD"></ApplicationRef></WorkflowBusinessRule>
<WorkflowBusinessRuleHandler id="id63" name="EPM-check-condition">
<ApplicationRef application="Teamcenter" label="j1UlYfaa1cuxKD" version="j1UlYfaa1cuxKD"></ApplicationRef>
<Arguments id="id64" type="string">
<UserValue title="handler_argument" value="-source_task=Condition OK?"></UserValue>
<UserValue title="handler_argument" value="-decision=false"></UserValue></Arguments></WorkflowBusinessRuleHandler>
<WorkflowHandler id="id65" name="EPM-inherit">
<ApplicationRef application="Teamcenter" label="j1XlYfaa1cuxKD" version="j1XlYfaa1cuxKD"></ApplicationRef></WorkflowHandler>
<WorkflowAction id="id66" parentRef="" actionType="4" ruleRefs="#id67">
<ApplicationRef application="Teamcenter" label="j1alYfaa1cuxKD" version="j1alYfaa1cuxKD"></ApplicationRef></WorkflowAction>
<WorkflowBusinessRule id="id67" ruleQuorum="1" ruleHandlerRefs="#id68">
<ApplicationRef application="Teamcenter" label="j1blYfaa1cuxKD" version="j1blYfaa1cuxKD"></ApplicationRef></WorkflowBusinessRule>
<WorkflowBusinessRuleHandler id="id68" name="EPM-hold">
<ApplicationRef application="Teamcenter" label="j1dlYfaa1cuxKD" version="j1dlYfaa1cuxKD"></ApplicationRef></WorkflowBusinessRuleHandler>
<WorkflowTemplate id="id69" name="Review Error  Report" originalId="C_blhu5n1cuxKD" signoffQuorum="0" parentTaskTemplateRef="#id2" objectType="EPMDoTaskTemplate" iconKey="doTask" dependencyTaskTemplateRefs="#id55" showInProcessStage="true" location="99,77,4,64,26c,64" actions="#id71 #id74">
<ApplicationRef application="Teamcenter" label="jxQlYfaa1cuxKD" version="jxQlYfaa1cuxKD"></ApplicationRef>
<UserData id="id70" type="reference">
<UserValue title="startDependencyTaskRef" value="2" dataRef="#id55"></UserValue></UserData></WorkflowTemplate>
<WorkflowAction id="id71" parentRef="" actionType="4" ruleRefs="#id72">
<ApplicationRef application="Teamcenter" label="jxRlYfaa1cuxKD" version="jxRlYfaa1cuxKD"></ApplicationRef></WorkflowAction>
<WorkflowBusinessRule id="id72" ruleQuorum="-1" ruleHandlerRefs="#id73">
<ApplicationRef application="Teamcenter" label="jxSlYfaa1cuxKD" version="jxSlYfaa1cuxKD"></ApplicationRef></WorkflowBusinessRule>
<WorkflowBusinessRuleHandler id="id73" name="EPM-hold">
<ApplicationRef application="Teamcenter" label="jxUlYfaa1cuxKD" version="jxUlYfaa1cuxKD"></ApplicationRef></WorkflowBusinessRuleHandler>
<WorkflowAction id="id74" parentRef="" actionType="2" ruleRefs="#id75">
<ApplicationRef application="Teamcenter" label="jxYlYfaa1cuxKD" version="jxYlYfaa1cuxKD"></ApplicationRef></WorkflowAction>
<WorkflowBusinessRule id="id75" ruleQuorum="-1" ruleHandlerRefs="#id76">
<ApplicationRef application="Teamcenter" label="jxZlYfaa1cuxKD" version="jxZlYfaa1cuxKD"></ApplicationRef></WorkflowBusinessRule>
<WorkflowBusinessRuleHandler id="id76" name="EPM-check-condition">
<ApplicationRef application="Teamcenter" label="jxblYfaa1cuxKD" version="jxblYfaa1cuxKD"></ApplicationRef>
<Arguments id="id77" type="string">
<UserValue title="handler_argument" value="-source_task=Check Relation"></UserValue>
<UserValue title="handler_argument" value="-decision=false"></UserValue></Arguments></WorkflowBusinessRuleHandler>
<WorkflowAction id="id79" parentRef="" actionType="2" ruleRefs="#id80">
<ApplicationRef application="Teamcenter" label="j9clYfaa1cuxKD" version="j9clYfaa1cuxKD"></ApplicationRef></WorkflowAction>
<WorkflowBusinessRule id="id80" ruleQuorum="1" ruleHandlerRefs="#id81">
<ApplicationRef application="Teamcenter" label="j9dlYfaa1cuxKD" version="j9dlYfaa1cuxKD"></ApplicationRef></WorkflowBusinessRule>
<WorkflowBusinessRuleHandler id="id81" name="EPM-check-condition">
<ApplicationRef application="Teamcenter" label="j9flYfaa1cuxKD" version="j9flYfaa1cuxKD"></ApplicationRef>
<Arguments id="id82" type="string">
<UserValue title="handler_argument" value="-source_task=Check BOM Precise"></UserValue>
<UserValue title="handler_argument" value="-decision=ANY"></UserValue></Arguments></WorkflowBusinessRuleHandler>
<WorkflowAction id="id84" actionHandlerRefs="#id85" parentRef="" actionType="2">
<ApplicationRef application="Teamcenter" label="zVYlYfaa1cuxKD" version="zVYlYfaa1cuxKD"></ApplicationRef></WorkflowAction>
<WorkflowHandler id="id85" name="EPM-set-rule-based-protection">
<ApplicationRef application="Teamcenter" label="zVZlYfaa1cuxKD" version="zVZlYfaa1cuxKD"></ApplicationRef>
<Arguments id="id86" type="string">
<UserValue title="handler_argument" value="-acl=EPM Open"></UserValue></Arguments></WorkflowHandler>
<WorkflowAction id="id87" actionHandlerRefs="#id88" parentRef="" actionType="4">
<ApplicationRef application="Teamcenter" label="zVclYfaa1cuxKD" version="zVclYfaa1cuxKD"></ApplicationRef></WorkflowAction>
<WorkflowHandler id="id88" name="SBT-AH-cleanup-relations">
<ApplicationRef application="Teamcenter" label="zVdlYfaa1cuxKD" version="zVdlYfaa1cuxKD"></ApplicationRef></WorkflowHandler>
<WorkflowAction id="id90" parentRef="" actionType="4" ruleRefs="#id91">
<ApplicationRef application="Teamcenter" label="jtUlYfaa1cuxKD" version="jtUlYfaa1cuxKD"></ApplicationRef></WorkflowAction>
<WorkflowBusinessRule id="id91" ruleQuorum="-1" ruleHandlerRefs="#id92">
<ApplicationRef application="Teamcenter" label="jtVlYfaa1cuxKD" version="jtVlYfaa1cuxKD"></ApplicationRef></WorkflowBusinessRule>
<WorkflowBusinessRuleHandler id="id92" name="SBT-RH-part-has-released-bom-attached">
<ApplicationRef application="Teamcenter" label="jtXlYfaa1cuxKD" version="jtXlYfaa1cuxKD"></ApplicationRef>
<Arguments id="id93" type="string">
<UserValue title="handler_argument" value="status_allowed=Pre Release,Serial Release"></UserValue></Arguments></WorkflowBusinessRuleHandler>
<WorkflowAction id="id94" actionHandlerRefs="#id95" parentRef="" actionType="2">
<ApplicationRef application="Teamcenter" label="jtblYfaa1cuxKD" version="jtblYfaa1cuxKD"></ApplicationRef></WorkflowAction>
<WorkflowHandler id="id95" name="EPM-set-rule-based-protection">
<ApplicationRef application="Teamcenter" label="jtclYfaa1cuxKD" version="jtclYfaa1cuxKD"></ApplicationRef>
<Arguments id="id96" type="string">
<UserValue title="handler_argument" value="-acl=BT7_ResetACL"></UserValue></Arguments></WorkflowHandler>
<WorkflowAction id="id98" parentRef="" actionType="2" ruleRefs="#id99 #id102">
<ApplicationRef application="Teamcenter" label="zRalYfaa1cuxKD" version="zRalYfaa1cuxKD"></ApplicationRef></WorkflowAction>
<WorkflowBusinessRule id="id99" ruleQuorum="1" ruleHandlerRefs="#id100">
<ApplicationRef application="Teamcenter" label="zRblYfaa1cuxKD" version="zRblYfaa1cuxKD"></ApplicationRef></WorkflowBusinessRule>
<WorkflowBusinessRuleHandler id="id100" name="TCPB-RH-checkBomChildStatusList">
<ApplicationRef application="Teamcenter" label="zRdlYfaa1cuxKD" version="zRdlYfaa1cuxKD"></ApplicationRef>
<Arguments id="id101" type="string">
<UserValue title="handler_argument" value="-rule=BOM_Analysis"></UserValue>
<UserValue title="handler_argument" value="-statelist=10,60,BT7_ECO"></UserValue>
<UserValue title="handler_argument" value="-check_job=y"></UserValue>
<UserValue title="handler_argument" value="-log=all"></UserValue>
<UserValue title="handler_argument" value="-stop=n"></UserValue>
<UserValue title="handler_argument" value="-maxdepth=1"></UserValue>
<UserValue title="handler_argument" value="-set_task_result=Condition OK?"></UserValue></Arguments></WorkflowBusinessRuleHandler>
<WorkflowBusinessRule id="id102" ruleQuorum="-1" ruleHandlerRefs="#id103">
<ApplicationRef application="Teamcenter" label="zVQlYfaa1cuxKD" version="zVQlYfaa1cuxKD"></ApplicationRef></WorkflowBusinessRule>
<WorkflowBusinessRuleHandler id="id103" name="EPM-check-condition">
<ApplicationRef application="Teamcenter" label="zVSlYfaa1cuxKD" version="zVSlYfaa1cuxKD"></ApplicationRef>
<Arguments id="id104" type="string">
<UserValue title="handler_argument" value="-source_task=Check Relation"></UserValue>
<UserValue title="handler_argument" value="-decision=true"></UserValue></Arguments></WorkflowBusinessRuleHandler>
<WorkflowAction id="id106" actionHandlerRefs="#id107" parentRef="" actionType="2">
<ApplicationRef application="Teamcenter" label="zFWlYfaa1cuxKD" version="zFWlYfaa1cuxKD"></ApplicationRef></WorkflowAction>
<WorkflowHandler id="id107" name="EPM-set-rule-based-protection">
<ApplicationRef application="Teamcenter" label="zFXlYfaa1cuxKD" version="zFXlYfaa1cuxKD"></ApplicationRef>
<Arguments id="id108" type="string">
<UserValue title="handler_argument" value="-acl=BT7_ResetACL"></UserValue></Arguments></WorkflowHandler>
<WorkflowAction id="id110" actionHandlerRefs="#id114" parentRef="" actionType="2" ruleRefs="#id111">
<ApplicationRef application="Teamcenter" label="zJelYfaa1cuxKD" version="zJelYfaa1cuxKD"></ApplicationRef></WorkflowAction>
<WorkflowBusinessRule id="id111" ruleQuorum="-1" ruleHandlerRefs="#id112">
<ApplicationRef application="Teamcenter" label="zJflYfaa1cuxKD" version="zJflYfaa1cuxKD"></ApplicationRef></WorkflowBusinessRule>
<WorkflowBusinessRuleHandler id="id112" name="EPM-check-condition">
<ApplicationRef application="Teamcenter" label="zNRlYfaa1cuxKD" version="zNRlYfaa1cuxKD"></ApplicationRef>
<Arguments id="id113" type="string">
<UserValue title="handler_argument" value="-source_task=Condition OK?"></UserValue>
<UserValue title="handler_argument" value="-decision=true"></UserValue></Arguments></WorkflowBusinessRuleHandler>
<WorkflowHandler id="id114" name="EPM-inherit">
<ApplicationRef application="Teamcenter" label="zNUlYfaa1cuxKD" version="zNUlYfaa1cuxKD"></ApplicationRef></WorkflowHandler>
<WorkflowAction id="id116" parentRef="" actionType="4" ruleRefs="#id117">
<ApplicationRef application="Teamcenter" label="zNflYfaa1cuxKD" version="zNflYfaa1cuxKD"></ApplicationRef></WorkflowAction>
<WorkflowBusinessRule id="id117" ruleQuorum="-1" ruleHandlerRefs="#id118">
<ApplicationRef application="Teamcenter" label="zRQlYfaa1cuxKD" version="zRQlYfaa1cuxKD"></ApplicationRef></WorkflowBusinessRule>
<WorkflowBusinessRuleHandler id="id118" name="SBT-RH-check-target-released">
<ApplicationRef application="Teamcenter" label="zRSlYfaa1cuxKD" version="zRSlYfaa1cuxKD"></ApplicationRef>
<Arguments id="id119" type="string">
<UserValue title="handler_argument" value="status=Pre Release,Serial Release"></UserValue></Arguments></WorkflowBusinessRuleHandler>
<WorkflowAction id="id120" parentRef="" actionType="2">
<ApplicationRef application="Teamcenter" label="zRWlYfaa1cuxKD" version="zRWlYfaa1cuxKD"></ApplicationRef></WorkflowAction>
<WorkflowAction id="id122" actionHandlerRefs="#id123 #id124" parentRef="" actionType="4">
<ApplicationRef application="Teamcenter" label="j5TlYfaa1cuxKD" version="j5TlYfaa1cuxKD"></ApplicationRef></WorkflowAction>
<WorkflowHandler id="id123" name="SBT-AH-write-uid-of-current-workflow-to-file-and-attach-it">
<ApplicationRef application="Teamcenter" label="j5UlYfaa1cuxKD" version="j5UlYfaa1cuxKD"></ApplicationRef></WorkflowHandler>
<WorkflowHandler id="id124" name="EPM-create-sub-process">
<ApplicationRef application="Teamcenter" label="j5WlYfaa1cuxKD" version="j5WlYfaa1cuxKD"></ApplicationRef>
<Arguments id="id125" type="string">
<UserValue title="handler_argument" value="-template=BT7_GenAddElectronic3dRepresentation"></UserValue>
<UserValue title="handler_argument" value="-from_attach=All"></UserValue>
<UserValue title="handler_argument" value="-to_attach=All"></UserValue>
<UserValue title="handler_argument" value="-include_type=BT7_ComponentRevision,Text"></UserValue>
<UserValue title="handler_argument" value="-multiple_processes"></UserValue>
<UserValue title="handler_argument" value="-dependency=PR:Hold Parent Task::BT7_GenAddElectronic3dRepresentation:Final Task"></UserValue></Arguments></WorkflowHandler>
<WorkflowAction id="id126" parentRef="" actionType="2" ruleRefs="#id127">
<ApplicationRef application="Teamcenter" label="j5ZlYfaa1cuxKD" version="j5ZlYfaa1cuxKD"></ApplicationRef></WorkflowAction>
<WorkflowBusinessRule id="id127" ruleQuorum="-1" ruleHandlerRefs="#id128">
<ApplicationRef application="Teamcenter" label="j5alYfaa1cuxKD" version="j5alYfaa1cuxKD"></ApplicationRef></WorkflowBusinessRule>
<WorkflowBusinessRuleHandler id="id128" name="EPM-check-condition">
<ApplicationRef application="Teamcenter" label="j5clYfaa1cuxKD" version="j5clYfaa1cuxKD"></ApplicationRef>
<Arguments id="id129" type="string">
<UserValue title="handler_argument" value="-source_task=Already PreReleased?"></UserValue>
<UserValue title="handler_argument" value="-decision=false"></UserValue></Arguments></WorkflowBusinessRuleHandler>
<WorkflowAction id="id131" parentRef="" actionType="2">
<ApplicationRef application="Teamcenter" label="zFclYfaa1cuxKD" version="zFclYfaa1cuxKD"></ApplicationRef></WorkflowAction>
<WorkflowAction id="id133" actionHandlerRefs="#id134" parentRef="" actionType="2">
<ApplicationRef application="Teamcenter" label="zJQlYfaa1cuxKD" version="zJQlYfaa1cuxKD"></ApplicationRef></WorkflowAction>
<WorkflowHandler id="id134" name="EPM-set-rule-based-protection">
<ApplicationRef application="Teamcenter" label="zJRlYfaa1cuxKD" version="zJRlYfaa1cuxKD"></ApplicationRef>
<Arguments id="id135" type="string">
<UserValue title="handler_argument" value="-acl=EPM Open"></UserValue></Arguments></WorkflowHandler>
<WorkflowAction id="id136" actionHandlerRefs="#id137" parentRef="" actionType="4">
<ApplicationRef application="Teamcenter" label="zJUlYfaa1cuxKD" version="zJUlYfaa1cuxKD"></ApplicationRef></WorkflowAction>
<WorkflowHandler id="id137" name="SBT-AH-cleanup-relations">
<ApplicationRef application="Teamcenter" label="zJVlYfaa1cuxKD" version="zJVlYfaa1cuxKD"></ApplicationRef></WorkflowHandler>
<WorkflowAction id="id139" actionHandlerRefs="#id140 #id142 #id144 #id146 #id148 #id150 #id152" parentRef="" actionType="2">
<ApplicationRef application="Teamcenter" label="jlWlYfaa1cuxKD" version="jlWlYfaa1cuxKD"></ApplicationRef></WorkflowAction>
<WorkflowHandler id="id140" name="EPM-set-rule-based-protection">
<ApplicationRef application="Teamcenter" label="jlXlYfaa1cuxKD" version="jlXlYfaa1cuxKD"></ApplicationRef>
<Arguments id="id141" type="string">
<UserValue title="handler_argument" value="-acl=EPM Open"></UserValue></Arguments></WorkflowHandler>
<WorkflowHandler id="id142" name="EPM-create-status">
<ApplicationRef application="Teamcenter" label="jlZlYfaa1cuxKD" version="jlZlYfaa1cuxKD"></ApplicationRef>
<Arguments id="id143" type="string">
<UserValue title="handler_argument" value="-status=10"></UserValue></Arguments></WorkflowHandler>
<WorkflowHandler id="id144" name="EPM-attach-related-objects">
<ApplicationRef application="Teamcenter" label="jlblYfaa1cuxKD" version="jlblYfaa1cuxKD"></ApplicationRef>
<Arguments id="id145" type="string">
<UserValue title="handler_argument" value="-relation=IMAN_master_form"></UserValue>
<UserValue title="handler_argument" value="-attachment=target"></UserValue></Arguments></WorkflowHandler>
<WorkflowHandler id="id146" name="EPM-attach-related-objects">
<ApplicationRef application="Teamcenter" label="jldlYfaa1cuxKD" version="jldlYfaa1cuxKD"></ApplicationRef>
<Arguments id="id147" type="string">
<UserValue title="handler_argument" value="-relation=PSBOMViewRevision"></UserValue>
<UserValue title="handler_argument" value="-attachment=target"></UserValue></Arguments></WorkflowHandler>
<WorkflowHandler id="id148" name="EPM-attach-related-objects">
<ApplicationRef application="Teamcenter" label="jlflYfaa1cuxKD" version="jlflYfaa1cuxKD"></ApplicationRef>
<Arguments id="id149" type="string">
<UserValue title="handler_argument" value="-relation=TC_Attaches"></UserValue>
<UserValue title="handler_argument" value="-attachment=target"></UserValue></Arguments></WorkflowHandler>
<WorkflowHandler id="id150" name="EPM-attach-related-objects">
<ApplicationRef application="Teamcenter" label="jpRlYfaa1cuxKD" version="jpRlYfaa1cuxKD"></ApplicationRef>
<Arguments id="id151" type="string">
<UserValue title="handler_argument" value="-relation=IMAN_specification"></UserValue>
<UserValue title="handler_argument" value="-attachment=target"></UserValue></Arguments></WorkflowHandler>
<WorkflowHandler id="id152" name="EPM-attach-related-objects">
<ApplicationRef application="Teamcenter" label="jpTlYfaa1cuxKD" version="jpTlYfaa1cuxKD"></ApplicationRef>
<Arguments id="id153" type="string">
<UserValue title="handler_argument" value="-relation=IMAN_Rendering"></UserValue>
<UserValue title="handler_argument" value="-attachment=target"></UserValue></Arguments></WorkflowHandler>
<WorkflowAction id="id154" actionHandlerRefs="#id155 #id157 #id159 #id161 #id163" parentRef="" actionType="4">
<ApplicationRef application="Teamcenter" label="jpWlYfaa1cuxKD" version="jpWlYfaa1cuxKD"></ApplicationRef></WorkflowAction>
<WorkflowHandler id="id155" name="EPM-set-status">
<ApplicationRef application="Teamcenter" label="jpXlYfaa1cuxKD" version="jpXlYfaa1cuxKD"></ApplicationRef>
<Arguments id="id156" type="string">
<UserValue title="handler_argument" value="-action=append"></UserValue></Arguments></WorkflowHandler>
<WorkflowHandler id="id157" name="SBT-AH-set-latest-release-status">
<ApplicationRef application="Teamcenter" label="jpZlYfaa1cuxKD" version="jpZlYfaa1cuxKD"></ApplicationRef>
<Arguments id="id158" type="string">
<UserValue title="handler_argument" value="object_type=ItemRevision"></UserValue>
<UserValue title="handler_argument" value="props=bt7_RevLastStatus"></UserValue></Arguments></WorkflowHandler>
<WorkflowHandler id="id159" name="TCPB-AH-releasePrevItemRev">
<ApplicationRef application="Teamcenter" label="jpblYfaa1cuxKD" version="jpblYfaa1cuxKD"></ApplicationRef>
<Arguments id="id160" type="string">
<UserValue title="handler_argument" value="-status=$NONE"></UserValue>
<UserValue title="handler_argument" value="-rev_status=none,5,10"></UserValue>
<UserValue title="handler_argument" value="-latest=latest specified"></UserValue>
<UserValue title="handler_argument" value="-proc_name=BT7_SetProperty"></UserValue>
<UserValue title="handler_argument" value="-subprocess"></UserValue>
<UserValue title="handler_argument" value="-job_name=$ObjectString"></UserValue>
<UserValue title="handler_argument" value="-single_process"></UserValue></Arguments></WorkflowHandler>
<WorkflowHandler id="id161" name="TCPB-AH-releasePrevItemRev">
<ApplicationRef application="Teamcenter" label="jpdlYfaa1cuxKD" version="jpdlYfaa1cuxKD"></ApplicationRef>
<Arguments id="id162" type="string">
<UserValue title="handler_argument" value="-status=90"></UserValue>
<UserValue title="handler_argument" value="-rev_status=none,5,10"></UserValue>
<UserValue title="handler_argument" value="-latest=latest specified"></UserValue>
<UserValue title="handler_argument" value="-relation=IMAN_specification"></UserValue></Arguments></WorkflowHandler>
<WorkflowHandler id="id163" name="EPM-set-property">
<ApplicationRef application="Teamcenter" label="jpflYfaa1cuxKD" version="jpflYfaa1cuxKD"></ApplicationRef>
<Arguments id="id164" type="string">
<UserValue title="handler_argument" value="-property=bt7_ApprDate_2"></UserValue>
<UserValue title="handler_argument" value="-value=PROP::date_released"></UserValue>
<UserValue title="handler_argument" value="-from_attach=TARGET"></UserValue>
<UserValue title="handler_argument" value="-to_attach=TARGET"></UserValue>
<UserValue title="handler_argument" value="-include_type=BT7_ComponentRevision,BT7_DocumentRevision,BT7_MaterialRevision,BT7_ProductRevision,BT7_SoftwareRevision,BT7_ToolRevision,BT7_ToolPartRevision"></UserValue></Arguments></WorkflowHandler>
<WorkflowTemplate id="id165" name="Send Notification" originalId="C_Rlhu5n1cuxKD" signoffQuorum="0" parentTaskTemplateRef="#id2" objectType="EPMTaskTemplate" iconKey="task" dependencyTaskTemplateRefs="#id166" showInProcessStage="false" location="415,6e,4,64,26c,64" actions="#id184 #id187">
<ApplicationRef application="Teamcenter" label="j9RlYfaa1cuxKD" version="j9RlYfaa1cuxKD"></ApplicationRef>
<UserData id="id183" type="reference">
<UserValue title="startDependencyTaskRef" value="2" dataRef="#id166"></UserValue></UserData></WorkflowTemplate>
<WorkflowTemplate id="id166" name="Valid Version set" originalId="SKXlhu5n1cuxKD" signoffQuorum="0" parentTaskTemplateRef="#id2" objectType="EPMDoTaskTemplate" iconKey="doTask" dependencyTaskTemplateRefs="#id167" showInProcessStage="true" location="39c,6f,4,64,26c,64" actions="#id179">
<ApplicationRef application="Teamcenter" label="zBUlYfaa1cuxKD" version="zBUlYfaa1cuxKD"></ApplicationRef>
<UserData id="id178" type="reference">
<UserValue title="startDependencyTaskRef" value="2" dataRef="#id167"></UserValue></UserData></WorkflowTemplate>
<WorkflowTemplate id="id167" name="Or 3" originalId="SmZlhu5n1cuxKD" signoffQuorum="0" parentTaskTemplateRef="#id2" objectType="EPMOrTaskTemplate" iconKey="orTask" dependencyTaskTemplateRefs="#id51 #id168" showInProcessStage="false" location="345,70,4,64,26c,64" actions="#id174">
<ApplicationRef application="Teamcenter" label="zBclYfaa1cuxKD" version="zBclYfaa1cuxKD"></ApplicationRef>
<UserData id="id173" type="reference">
<UserValue title="startDependencyTaskRef" value="2" dataRef="#id51"></UserValue>
<UserValue title="startDependencyTaskRef" value="2" dataRef="#id168"></UserValue></UserData></WorkflowTemplate>
<WorkflowTemplate id="id168" name="CreateImage" originalId="SqSlhu5n1cuxKD" signoffQuorum="0" parentTaskTemplateRef="#id2" objectType="EPMDoTaskTemplate" iconKey="doTask" dependencyTaskTemplateRefs="#id47" showInProcessStage="true" location="297,163,4,64,26c,64" actions="#id170">
<ApplicationRef application="Teamcenter" label="zNYlYfaa1cuxKD" version="zNYlYfaa1cuxKD"></ApplicationRef>
<UserData id="id169" type="reference">
<UserValue title="startDependencyTaskRef" value="2" dataRef="#id47"></UserValue></UserData></WorkflowTemplate>
<WorkflowAction id="id170" actionHandlerRefs="#id171" parentRef="" actionType="2">
<ApplicationRef application="Teamcenter" label="zNZlYfaa1cuxKD" version="zNZlYfaa1cuxKD"></ApplicationRef></WorkflowAction>
<WorkflowHandler id="id171" name="EPM-create-sub-process">
<ApplicationRef application="Teamcenter" label="zNalYfaa1cuxKD" version="zNalYfaa1cuxKD"></ApplicationRef>
<Arguments id="id172" type="string">
<UserValue title="handler_argument" value="-template=BT7_CRI_PreRelease"></UserValue>
<UserValue title="handler_argument" value="-from_attach=all"></UserValue>
<UserValue title="handler_argument" value="-to_attach=target"></UserValue></Arguments></WorkflowHandler>
<WorkflowAction id="id174" parentRef="" actionType="2" ruleRefs="#id175">
<ApplicationRef application="Teamcenter" label="zBdlYfaa1cuxKD" version="zBdlYfaa1cuxKD"></ApplicationRef></WorkflowAction>
<WorkflowBusinessRule id="id175" ruleQuorum="1" ruleHandlerRefs="#id176">
<ApplicationRef application="Teamcenter" label="zBelYfaa1cuxKD" version="zBelYfaa1cuxKD"></ApplicationRef></WorkflowBusinessRule>
<WorkflowBusinessRuleHandler id="id176" name="EPM-check-condition">
<ApplicationRef application="Teamcenter" label="zFQlYfaa1cuxKD" version="zFQlYfaa1cuxKD"></ApplicationRef>
<Arguments id="id177" type="string">
<UserValue title="handler_argument" value="-source_task=Already PreReleased?"></UserValue>
<UserValue title="handler_argument" value="-decision=true"></UserValue></Arguments></WorkflowBusinessRuleHandler>
<WorkflowAction id="id179" actionHandlerRefs="#id180 #id181" parentRef="" actionType="2">
<ApplicationRef application="Teamcenter" label="zBVlYfaa1cuxKD" version="zBVlYfaa1cuxKD"></ApplicationRef></WorkflowAction>
<WorkflowHandler id="id180" name="EPM-inherit">
<ApplicationRef application="Teamcenter" label="zBWlYfaa1cuxKD" version="zBWlYfaa1cuxKD"></ApplicationRef></WorkflowHandler>
<WorkflowHandler id="id181" name="EPM-create-sub-process">
<ApplicationRef application="Teamcenter" label="zBYlYfaa1cuxKD" version="zBYlYfaa1cuxKD"></ApplicationRef>
<Arguments id="id182" type="string">
<UserValue title="handler_argument" value="-template=BT7_Check_ValidVersonSet"></UserValue>
<UserValue title="handler_argument" value="-from_attach=all"></UserValue>
<UserValue title="handler_argument" value="-to_attach=target"></UserValue></Arguments></WorkflowHandler>
<WorkflowAction id="id184" actionHandlerRefs="#id185" parentRef="" actionType="2">
<ApplicationRef application="Teamcenter" label="j9SlYfaa1cuxKD" version="j9SlYfaa1cuxKD"></ApplicationRef></WorkflowAction>
<WorkflowHandler id="id185" name="EPM-set-rule-based-protection">
<ApplicationRef application="Teamcenter" label="j9TlYfaa1cuxKD" version="j9TlYfaa1cuxKD"></ApplicationRef>
<Arguments id="id186" type="string">
<UserValue title="handler_argument" value="-acl=EPM Open"></UserValue></Arguments></WorkflowHandler>
<WorkflowAction id="id187" actionHandlerRefs="#id188" parentRef="" actionType="4">
<ApplicationRef application="Teamcenter" label="j9WlYfaa1cuxKD" version="j9WlYfaa1cuxKD"></ApplicationRef></WorkflowAction>
<WorkflowHandler id="id188" name="SBT-AH-send-notification">
<ApplicationRef application="Teamcenter" label="j9XlYfaa1cuxKD" version="j9XlYfaa1cuxKD"></ApplicationRef>
<Arguments id="id189" type="string">
<UserValue title="handler_argument" value="subject=Objects have Status PR"></UserValue>
<UserValue title="handler_argument" value="message=Status PR:"></UserValue></Arguments></WorkflowHandler>
<WorkflowTemplate id="id190" name="Or 4" originalId="SWVlhu5n1cuxKD" signoffQuorum="0" parentTaskTemplateRef="#id2" objectType="EPMOrTaskTemplate" iconKey="orTask" dependencyTaskTemplateRefs="#id165 #id11 #id39 #id58 #id69" showInProcessStage="false" location="42b,100,4,64,26c,64" actions="#id192">
<ApplicationRef application="Teamcenter" label="zJZlYfaa1cuxKD" version="zJZlYfaa1cuxKD"></ApplicationRef>
<UserData id="id191" type="reference">
<UserValue title="startDependencyTaskRef" value="2" dataRef="#id165"></UserValue>
<UserValue title="startDependencyTaskRef" value="2" dataRef="#id11"></UserValue>
<UserValue title="startDependencyTaskRef" value="2" dataRef="#id39"></UserValue>
<UserValue title="failDependencyTaskRef" value="10" dataRef="#id58"></UserValue>
<UserValue title="failDependencyTaskRef" value="10" dataRef="#id69"></UserValue></UserData></WorkflowTemplate>
<WorkflowAction id="id192" parentRef="" actionType="2">
<ApplicationRef application="Teamcenter" label="zJalYfaa1cuxKD" version="zJalYfaa1cuxKD"></ApplicationRef></WorkflowAction>
<WorkflowAction id="id194" actionHandlerRefs="#id212 #id214 #id216 #id217" parentRef="" actionType="2" ruleRefs="#id195 #id199 #id202 #id207 #id209">
<ApplicationRef application="Teamcenter" label="jBZlYfaa1cuxKD" version="jBZlYfaa1cuxKD"></ApplicationRef></WorkflowAction>
<WorkflowBusinessRule id="id195" ruleQuorum="2" ruleHandlerRefs="#id196 #id198">
<ApplicationRef application="Teamcenter" label="jBalYfaa1cuxKD" version="jBalYfaa1cuxKD"></ApplicationRef></WorkflowBusinessRule>
<WorkflowBusinessRuleHandler id="id196" name="EPM-check-object-properties">
<ApplicationRef application="Teamcenter" label="jBclYfaa1cuxKD" version="jBclYfaa1cuxKD"></ApplicationRef>
<Arguments id="id197" type="string">
<UserValue title="handler_argument" value="-include_type=BT7_Product"></UserValue>
<UserValue title="handler_argument" value="-attachment=reference"></UserValue>
<UserValue title="handler_argument" value="-property=bt7_articletype"></UserValue></Arguments></WorkflowBusinessRuleHandler>
<WorkflowBusinessRuleHandler id="id198" name="SBT-RH-checkRevsInProc">
<ApplicationRef application="Teamcenter" label="jBelYfaa1cuxKD" version="jBelYfaa1cuxKD"></ApplicationRef></WorkflowBusinessRuleHandler>
<WorkflowBusinessRule id="id199" ruleQuorum="-1" ruleHandlerRefs="#id200">
<ApplicationRef application="Teamcenter" label="jFRlYfaa1cuxKD" version="jFRlYfaa1cuxKD"></ApplicationRef></WorkflowBusinessRule>
<WorkflowBusinessRuleHandler id="id200" name="EPM-check-object-properties">
<ApplicationRef application="Teamcenter" label="jFTlYfaa1cuxKD" version="jFTlYfaa1cuxKD"></ApplicationRef>
<Arguments id="id201" type="string">
<UserValue title="handler_argument" value="-include_type=BT7_MaterialRevision"></UserValue>
<UserValue title="handler_argument" value="-property=bt7_RevLastStatus"></UserValue>
<UserValue title="handler_argument" value="-value=60"></UserValue>
<UserValue title="handler_argument" value="-attachment=reference"></UserValue></Arguments></WorkflowBusinessRuleHandler>
<WorkflowBusinessRule id="id202" ruleQuorum="1" ruleHandlerRefs="#id203 #id205">
<ApplicationRef application="Teamcenter" label="jFWlYfaa1cuxKD" version="jFWlYfaa1cuxKD"></ApplicationRef></WorkflowBusinessRule>
<WorkflowBusinessRuleHandler id="id203" name="EPM-check-object-properties">
<ApplicationRef application="Teamcenter" label="jFYlYfaa1cuxKD" version="jFYlYfaa1cuxKD"></ApplicationRef>
<Arguments id="id204" type="string">
<UserValue title="handler_argument" value="-include_type=UGMASTER,UGPART"></UserValue>
<UserValue title="handler_argument" value="-property=bt7_cp_CheckClass"></UserValue>
<UserValue title="handler_argument" value="-value=1"></UserValue>
<UserValue title="handler_argument" value="-attachment=reference"></UserValue></Arguments></WorkflowBusinessRuleHandler>
<WorkflowBusinessRuleHandler id="id205" name="EPM-check-object-properties">
<ApplicationRef application="Teamcenter" label="jFalYfaa1cuxKD" version="jFalYfaa1cuxKD"></ApplicationRef>
<Arguments id="id206" type="string">
<UserValue title="handler_argument" value="-include_type=UGMASTER,UGPART"></UserValue>
<UserValue title="handler_argument" value="-property=bt7_cp_CheckClass"></UserValue>
<UserValue title="handler_argument" value="-value=2"></UserValue>
<UserValue title="handler_argument" value="-attachment=reference"></UserValue></Arguments></WorkflowBusinessRuleHandler>
<WorkflowBusinessRule id="id207" ruleQuorum="-1" ruleHandlerRefs="#id208">
<ApplicationRef application="Teamcenter" label="jFdlYfaa1cuxKD" version="jFdlYfaa1cuxKD"></ApplicationRef></WorkflowBusinessRule>
<WorkflowBusinessRuleHandler id="id208" name="SBT-RH-check-targets-same">
<ApplicationRef application="Teamcenter" label="jFflYfaa1cuxKD" version="jFflYfaa1cuxKD"></ApplicationRef></WorkflowBusinessRuleHandler>
<WorkflowBusinessRule id="id209" ruleQuorum="-1" ruleHandlerRefs="#id210">
<ApplicationRef application="Teamcenter" label="jJSlYfaa1cuxKD" version="jJSlYfaa1cuxKD"></ApplicationRef></WorkflowBusinessRule>
<WorkflowBusinessRuleHandler id="id210" name="EPM-check-object-properties">
<ApplicationRef application="Teamcenter" label="jJUlYfaa1cuxKD" version="jJUlYfaa1cuxKD"></ApplicationRef>
<Arguments id="id211" type="string">
<UserValue title="handler_argument" value="-include_type=BT7_DocumentRevision,BT7_ProdTypeKeyRevision"></UserValue>
<UserValue title="handler_argument" value="-property=bt7_documentClass,bt7_documentSubClass,bt7_documentSNType"></UserValue>
<UserValue title="handler_argument" value="-attachment=target"></UserValue></Arguments></WorkflowBusinessRuleHandler>
<WorkflowHandler id="id212" name="EPM-remove-objects">
<ApplicationRef application="Teamcenter" label="jNRlYfaa1cuxKD" version="jNRlYfaa1cuxKD"></ApplicationRef>
<Arguments id="id213" type="string">
<UserValue title="handler_argument" value="-remove_refs=(Dataset)"></UserValue></Arguments></WorkflowHandler>
<WorkflowHandler id="id214" name="EPM-assign-team-selector">
<ApplicationRef application="Teamcenter" label="jNTlYfaa1cuxKD" version="jNTlYfaa1cuxKD"></ApplicationRef>
<Arguments id="id215" type="string">
<UserValue title="handler_argument" value="-assignee=$PROCESS_OWNER"></UserValue></Arguments></WorkflowHandler>
<WorkflowHandler id="id216" name="EPM-auto-assign-rest">
<ApplicationRef application="Teamcenter" label="jNVlYfaa1cuxKD" version="jNVlYfaa1cuxKD"></ApplicationRef></WorkflowHandler>
<WorkflowHandler id="id217" name="EPM-remove-objects">
<ApplicationRef application="Teamcenter" label="jNXlYfaa1cuxKD" version="jNXlYfaa1cuxKD"></ApplicationRef>
<Arguments id="id218" type="string">
<UserValue title="handler_argument" value="-remove_refs=BT7_MaterialRevision"></UserValue></Arguments></WorkflowHandler>
<WorkflowAction id="id219" parentRef="" actionType="100" ruleRefs="#id220">
<ApplicationRef application="Teamcenter" label="jNalYfaa1cuxKD" version="jNalYfaa1cuxKD"></ApplicationRef></WorkflowAction>
<WorkflowBusinessRule id="id220" ruleQuorum="3" ruleHandlerRefs="#id221 #id223 #id225">
<ApplicationRef application="Teamcenter" label="jNblYfaa1cuxKD" version="jNblYfaa1cuxKD"></ApplicationRef></WorkflowBusinessRule>
<WorkflowBusinessRuleHandler id="id221" name="EPM-check-target-object">
<ApplicationRef application="Teamcenter" label="jNdlYfaa1cuxKD" version="jNdlYfaa1cuxKD"></ApplicationRef>
<Arguments id="id222" type="string">
<UserValue title="handler_argument" value="-allowed_status=NONE,5,10"></UserValue></Arguments></WorkflowBusinessRuleHandler>
<WorkflowBusinessRuleHandler id="id223" name="EPM-check-target-object">
<ApplicationRef application="Teamcenter" label="jNflYfaa1cuxKD" version="jNflYfaa1cuxKD"></ApplicationRef>
<Arguments id="id224" type="string">
<UserValue title="handler_argument" value="-disallowed_status=60,90,98"></UserValue></Arguments></WorkflowBusinessRuleHandler>
<WorkflowBusinessRuleHandler id="id225" name="EPM-validate-target-objects">
<ApplicationRef application="Teamcenter" label="jRRlYfaa1cuxKD" version="jRRlYfaa1cuxKD"></ApplicationRef>
<Arguments id="id226" type="string">
<UserValue title="handler_argument" value="-exclude_type=BT7_ChangeNoticeRevision,BT7_CommonCompRevision"></UserValue></Arguments></WorkflowBusinessRuleHandler>
<WorkflowAction id="id227" actionHandlerRefs="#id228 #id230 #id232 #id234" parentRef="" actionType="1">
<ApplicationRef application="Teamcenter" label="jRVlYfaa1cuxKD" version="jRVlYfaa1cuxKD"></ApplicationRef></WorkflowAction>
<WorkflowHandler id="id228" name="EPM-attach-related-objects">
<ApplicationRef application="Teamcenter" label="jRWlYfaa1cuxKD" version="jRWlYfaa1cuxKD"></ApplicationRef>
<Arguments id="id229" type="string">
<UserValue title="handler_argument" value="-relation=Mat1UsesMaterial"></UserValue>
<UserValue title="handler_argument" value="-attachment=reference"></UserValue></Arguments></WorkflowHandler>
<WorkflowHandler id="id230" name="EPM-attach-related-objects">
<ApplicationRef application="Teamcenter" label="jRYlYfaa1cuxKD" version="jRYlYfaa1cuxKD"></ApplicationRef>
<Arguments id="id231" type="string">
<UserValue title="handler_argument" value="-relation=PSBOMViewRevision"></UserValue>
<UserValue title="handler_argument" value="-attachment=target"></UserValue></Arguments></WorkflowHandler>
<WorkflowHandler id="id232" name="EPM-attach-related-objects">
<ApplicationRef application="Teamcenter" label="jRalYfaa1cuxKD" version="jRalYfaa1cuxKD"></ApplicationRef>
<Arguments id="id233" type="string">
<UserValue title="handler_argument" value="-relation=IMAN_specification"></UserValue>
<UserValue title="handler_argument" value="-attachment=reference"></UserValue></Arguments></WorkflowHandler>
<WorkflowHandler id="id234" name="EPM-attach-related-objects">
<ApplicationRef application="Teamcenter" label="jRclYfaa1cuxKD" version="jRclYfaa1cuxKD"></ApplicationRef>
<Arguments id="id235" type="string">
<UserValue title="handler_argument" value="-include_related_type=BT7_Product"></UserValue>
<UserValue title="handler_argument" value="-property=items_tag"></UserValue>
<UserValue title="handler_argument" value="-attachment=reference"></UserValue></Arguments></WorkflowHandler></PLMXML>